{
    "post": {
        "summary": "Create new dashboard version",
        "tags": ["dashboard"],
        "operationId": "createDashboardVersion",
        "parameters": [
            {
                "in": "path",
                "name": "dashboardId",
                "schema": {
                    "type": "string",
                    "format": "uuid"
                },
                "required": true
            }
        ],
        "requestBody": {
            "description": "New dashboard version specification",
            "required": true,
            "content": {
                "application/json": {
                    "schema": {
                        "$ref": "../schemas/CreateDashboard.json"
                    }
                }
            }
        },
        "responses": {
            "201": {
                "description": "Successfully created dashboard version",
                "content": {
                    "application/json": {
                        "schema": {
                            "allOf": [
                                {
                                    "$ref": "../schemas/Success.json"
                                },
                                {
                                    "properties": {
                                        "results": {
                                            "$ref": "../schemas/Dashboard.json"
                                        }
                                    },
                                    "required": ["results"]
                                }
                            ]
                        }
                    }
                }
            },
            "default": {
                "$ref": "../responses/ErrorResponse.json"
            }
        }
    }
}
